git_pile/__init__.py
git_pile/cli.py
git_pile/config.py
git_pile/genbranch.py
git_pile/genbranch_caching.py
git_pile/git_pile.py
git_pile/gitutil.py
git_pile/helpers.py
git_pile/pile.py
git_pile/data/git-cover-order.txt
git_pile-1.3.data/scripts/git-pile
home/ldmartin/.local/share/git-pile/bash_completion/git-pile-complete.sh
home/ldmartin/.local/share/man/man1/git-pile-am.1
home/ldmartin/.local/share/man/man1/git-pile-baseline.1
home/ldmartin/.local/share/man/man1/git-pile-destroy.1
home/ldmartin/.local/share/man/man1/git-pile-format-patch.1
home/ldmartin/.local/share/man/man1/git-pile-genbranch.1
home/ldmartin/.local/share/man/man1/git-pile-genpatches.1
home/ldmartin/.local/share/man/man1/git-pile-setup.1
home/ldmartin/.local/share/man/man1/git-pile.1
git_pile-1.3.dist-info/LICENSE
git_pile-1.3.dist-info/METADATA
git_pile-1.3.dist-info/WHEEL
git_pile-1.3.dist-info/top_level.txt
git_pile-1.3.dist-info/RECORD
