Metadata-Version: 2.1
Name: git-pile
Version: 1.3
Summary: Manage a pile of patches on top of git branches
Home-page: https://github.com/git-pile/git-pile
Maintainer: git-pile contributors
Maintainer-email: lucas.demarchi@intel.com
License: LGPLv2+
Platform: any
Classifier: Intended Audience :: Developers
Classifier: License :: OSI Approved
Classifier: Programming Language :: Python
Classifier: Topic :: Software Development
Classifier: Operating System :: POSIX
Classifier: Operating System :: Unix
Requires-Python: >=3.6
License-File: LICENSE
Provides-Extra: tests
Requires-Dist: coverage ~=6.5 ; extra == 'tests'
